{"LastUpdate":"2022-01-21T02:16:27.8597381+01:00","PopupMessage":null,"Vehicles":[{"ID":19803,"IDB":0,"IDC":0,"VType":4,"LType":4,"Lat":49.275639,"Lng":16.991291,"Bearing":90,"LineID":755,"LineName":"755","RouteID":2,"Course":"75551","LF":true,"Delay":0,"LastStopID":17423,"FinalStopID":30013,"IsInactive":false},{"ID":2654,"IDB":0,"IDC":0,"VType":2,"LType":2,"Lat":49.169411,"Lng":16.567415,"Bearing":45,"LineID":91,"LineName":"N91","RouteID":110,"Course":"09102","LF":true,"Delay":1,"LastStopID":1472,"FinalStopID":1322,"IsInactive":false},{"ID":7815,"IDB":0,"IDC":0,"VType":2,"LType":2,"Lat":49.276375,"Lng":16.606665,"Bearing":-1,"LineID":90,"LineName":"N90","RouteID":111,"Course":"09006","LF":true,"Delay":0,"LastStopID":1467,"FinalStopID":1248,"IsInactive":true},{"ID":2015,"IDB":0,"IDC":0,"VType":2,"LType":2,"Lat":49.203606,"Lng":16.489592,"Bearing":-1,"LineID":98,"LineName":"N98","RouteID":112,"Course":"09803","LF":true,"Delay":0,"LastStopID":1015,"FinalStopID":1208,"IsInactive":true},{"ID":7702,"IDB":0,"IDC":0,"VType":2,"LType":2,"Lat":49.202507,"Lng":16.688671,"Bearing":90,"LineID":97,"LineName":"N97","RouteID":109,"Course":"09704","LF":true,"Delay":2,"LastStopID":1238,"FinalStopID":1346,"IsInactive":false},{"ID":7096,"IDB":0,"IDC":0,"VType":2,"LType":2,"Lat":49.146248,"Lng":16.620516,"Bearing":225,"LineID":94,"LineName":"N94","RouteID":109,"Course":"09403","LF":true,"Delay":0,"LastStopID":1354,"FinalStopID":15134,"IsInactive":false},{"ID":2647,"IDB":0,"IDC":0,"VType":2,"LType":2,"Lat":49.229786,"Lng":16.617611,"Bearing":225,"LineID":92,"LineName":"N92","RouteID":110,"Course":"09202","LF":true,"Delay":1,"LastStopID":1348,"FinalStopID":1128,"IsInactive":false},{"ID":7030,"IDB":0,"IDC":0,"VType":2,"LType":2,"Lat":49.185596,"Lng":16.541252,"Bearing":-1,"LineID":97,"LineName":"N97","RouteID":111,"Course":"09701","LF":true,"Delay":0,"LastStopID":1209,"FinalStopID":1346,"IsInactive":true},{"ID":7698,"IDB":0,"IDC":0,"VType":2,"LType":2,"Lat":49.180038,"Lng":16.549992,"Bearing":315,"LineID":95,"LineName":"N95","RouteID":110,"Course":"09502","LF":true,"Delay":0,"LastStopID":1443,"FinalStopID":1223,"IsInactive":false},{"ID":2630,"IDB":0,"IDC":0,"VType":2,"LType":2,"Lat":49.21241,"Lng":16.562866,"Bearing":45,"LineID":92,"LineName":"N92","RouteID":109,"Course":"09806","LF":true,"Delay":0,"LastStopID":1215,"FinalStopID":1062,"IsInactive":false},{"ID":7701,"IDB":0,"IDC":0,"VType":2,"LType":2,"Lat":49.230663,"Lng":16.604622,"Bearing":0,"LineID":93,"LineName":"N93","RouteID":110,"Course":"09306","LF":true,"Delay":2,"LastStopID":1150,"FinalStopID":1707,"IsInactive":false},{"ID":7811,"IDB":0,"IDC":0,"VType":2,"LType":2,"Lat":49.21656,"Lng":16.563444,"Bearing":315,"LineID":89,"LineName":"N89","RouteID":109,"Course":"08902","LF":true,"Delay":3,"LastStopID":1651,"FinalStopID":1689,"IsInactive":false},{"ID":2010,"IDB":0,"IDC":0,"VType":2,"LType":2,"Lat":49.21315,"Lng":16.676155,"Bearing":0,"LineID":98,"LineName":"N98","RouteID":110,"Course":"09801","LF":true,"Delay":1,"LastStopID":1157,"FinalStopID":1208,"IsInactive":false},{"ID":7686,"IDB":0,"IDC":0,"VType":2,"LType":2,"Lat":49.136044,"Lng":16.653305,"Bearing":225,"LineID":95,"LineName":"N95","RouteID":109,"Course":"09504","LF":true,"Delay":1,"LastStopID":1693,"FinalStopID":1182,"IsInactive":false},{"ID":30381,"IDB":0,"IDC":0,"VType":5,"LType":5,"Lat":49.231572,"Lng":16.595859,"Bearing":315,"LineID":147,"LineName":"R8","RouteID":1105,"Course":"1105","LF":false,"Delay":0,"LastStopID":1286,"FinalStopID":17446,"IsInactive":false},{"ID":7088,"IDB":0,"IDC":0,"VType":2,"LType":2,"Lat":49.226921,"Lng":16.647469,"Bearing":45,"LineID":94,"LineName":"N94","RouteID":110,"Course":"09405","LF":true,"Delay":3,"LastStopID":1077,"FinalStopID":1452,"IsInactive":false},{"ID":2648,"IDB":0,"IDC":0,"VType":2,"LType":2,"Lat":49.217937,"Lng":16.553467,"Bearing":315,"LineID":98,"LineName":"N98","RouteID":109,"Course":"09804","LF":true,"Delay":0,"LastStopID":1215,"FinalStopID":1015,"IsInactive":false},{"ID":7032,"IDB":0,"IDC":0,"VType":2,"LType":2,"Lat":49.226742,"Lng":16.53536,"Bearing":-1,"LineID":89,"LineName":"N89","RouteID":112,"Course":"08901","LF":true,"Delay":0,"LastStopID":1689,"FinalStopID":1337,"IsInactive":false},{"ID":7814,"IDB":0,"IDC":0,"VType":2,"LType":4,"Lat":49.218349,"Lng":16.584709,"Bearing":-1,"LineID":600,"LineName":"600","RouteID":1049,"Course":"30098","LF":true,"Delay":0,"LastStopID":8450,"FinalStopID":1146,"IsInactive":true},{"ID":2013,"IDB":0,"IDC":0,"VType":2,"LType":2,"Lat":49.173927,"Lng":16.541756,"Bearing":-1,"LineID":96,"LineName":"N96","RouteID":111,"Course":"09601","LF":true,"Delay":0,"LastStopID":1037,"FinalStopID":16159,"IsInactive":true},{"ID":7034,"IDB":0,"IDC":0,"VType":2,"LType":2,"Lat":49.179443,"Lng":16.545898,"Bearing":-1,"LineID":95,"LineName":"N95","RouteID":111,"Course":"09501","LF":true,"Delay":0,"LastStopID":1223,"FinalStopID":1182,"IsInactive":true},{"ID":2644,"IDB":0,"IDC":0,"VType":2,"LType":2,"Lat":49.219563,"Lng":16.521305,"Bearing":-1,"LineID":92,"LineName":"N92","RouteID":112,"Course":"09206","LF":true,"Delay":0,"LastStopID":1062,"FinalStopID":1128,"IsInactive":false},{"ID":2014,"IDB":0,"IDC":0,"VType":2,"LType":2,"Lat":49.172184,"Lng":16.704403,"Bearing":135,"LineID":96,"LineName":"N96","RouteID":109,"Course":"09607","LF":true,"Delay":1,"LastStopID":1292,"FinalStopID":16159,"IsInactive":false},{"ID":2007,"IDB":0,"IDC":0,"VType":2,"LType":2,"Lat":49.230412,"Lng":16.578491,"Bearing":315,"LineID":99,"LineName":"N99","RouteID":110,"Course":"09901","LF":true,"Delay":4,"LastStopID":1664,"FinalStopID":1659,"IsInactive":false},{"ID":2005,"IDB":0,"IDC":0,"VType":2,"LType":2,"Lat":49.166172,"Lng":16.558561,"Bearing":0,"LineID":96,"LineName":"N96","RouteID":110,"Course":"09603","LF":true,"Delay":0,"LastStopID":1687,"FinalStopID":1037,"IsInactive":false},{"ID":2004,"IDB":0,"IDC":0,"VType":2,"LType":2,"Lat":49.201439,"Lng":16.657984,"Bearing":90,"LineID":99,"LineName":"N99","RouteID":109,"Course":"09905","LF":true,"Delay":3,"LastStopID":1403,"FinalStopID":1362,"IsInactive":false},{"ID":7695,"IDB":0,"IDC":0,"VType":2,"LType":2,"Lat":49.177578,"Lng":16.552555,"Bearing":270,"LineID":90,"LineName":"N90","RouteID":109,"Course":"09002","LF":true,"Delay":2,"LastStopID":1443,"FinalStopID":1248,"IsInactive":false},{"ID":7098,"IDB":0,"IDC":0,"VType":2,"LType":2,"Lat":49.12635,"Lng":16.604801,"Bearing":-1,"LineID":94,"LineName":"N94","RouteID":112,"Course":"09401","LF":true,"Delay":0,"LastStopID":15134,"FinalStopID":1452,"IsInactive":true},{"ID":2631,"IDB":0,"IDC":0,"VType":2,"LType":2,"Lat":49.240479,"Lng":16.583969,"Bearing":315,"LineID":91,"LineName":"N91","RouteID":109,"Course":"09104","LF":true,"Delay":4,"LastStopID":1167,"FinalStopID":1189,"IsInactive":false},{"ID":2649,"IDB":0,"IDC":0,"VType":2,"LType":2,"Lat":49.171509,"Lng":16.558945,"Bearing":-1,"LineID":91,"LineName":"N91","RouteID":111,"Course":"09110","LF":true,"Delay":0,"LastStopID":1322,"FinalStopID":13129,"IsInactive":true},{"ID":7807,"IDB":0,"IDC":0,"VType":2,"LType":2,"Lat":49.167904,"Lng":16.67557,"Bearing":135,"LineID":89,"LineName":"N89","RouteID":110,"Course":"08904","LF":true,"Delay":1,"LastStopID":1064,"FinalStopID":1337,"IsInactive":false},{"ID":2652,"IDB":0,"IDC":0,"VType":2,"LType":2,"Lat":49.314297,"Lng":16.54707,"Bearing":-1,"LineID":91,"LineName":"N91","RouteID":114,"Course":"09106","LF":true,"Delay":0,"LastStopID":13129,"FinalStopID":1322,"IsInactive":true},{"ID":30389,"IDB":0,"IDC":0,"VType":5,"LType":5,"Lat":49.177601,"Lng":16.608078,"Bearing":180,"LineID":147,"LineName":"R8","RouteID":1101,"Course":"1101","LF":false,"Delay":0,"LastStopID":17446,"FinalStopID":17446,"IsInactive":false},{"ID":7031,"IDB":0,"IDC":0,"VType":2,"LType":2,"Lat":49.19669,"Lng":16.536093,"Bearing":315,"LineID":97,"LineName":"N97","RouteID":110,"Course":"09703","LF":true,"Delay":1,"LastStopID":1607,"FinalStopID":1209,"IsInactive":false},{"ID":7684,"IDB":0,"IDC":0,"VType":2,"LType":2,"Lat":49.236084,"Lng":16.584164,"Bearing":270,"LineID":90,"LineName":"N90","RouteID":110,"Course":"09008","LF":true,"Delay":5,"LastStopID":1756,"FinalStopID":1467,"IsInactive":false},{"ID":2012,"IDB":0,"IDC":0,"VType":2,"LType":2,"Lat":49.202923,"Lng":16.716236,"Bearing":-1,"LineID":99,"LineName":"N99","RouteID":112,"Course":"09903","LF":true,"Delay":0,"LastStopID":1362,"FinalStopID":1659,"IsInactive":false},{"ID":7703,"IDB":0,"IDC":0,"VType":2,"LType":2,"Lat":49.217472,"Lng":16.561085,"Bearing":315,"LineID":93,"LineName":"N93","RouteID":109,"Course":"09308","LF":true,"Delay":2,"LastStopID":1651,"FinalStopID":1258,"IsInactive":false},{"ID":7801,"IDB":0,"IDC":0,"VType":2,"LType":2,"Lat":49.282749,"Lng":16.633789,"Bearing":-1,"LineID":93,"LineName":"N93","RouteID":108,"Course":"09302","LF":true,"Delay":50,"LastStopID":1554,"FinalStopID":1707,"IsInactive":true}]}